collective.js.fileupload-9.12.3.post2-py2.7-nspkg.pth
collective/js/fileupload/testing.py
collective/js/fileupload/configure.zcml
collective/js/fileupload/__init__.py
collective/js/fileupload/resources/img/progressbar.gif
collective/js/fileupload/resources/img/loading.gif
collective/js/fileupload/resources/js/app.js
collective/js/fileupload/resources/js/jquery.fileupload-jquery-ui.js
collective/js/fileupload/resources/js/jquery.iframe-transport.js
collective/js/fileupload/resources/js/jquery.fileupload-video.js
collective/js/fileupload/resources/js/jquery.fileupload-ui.js
collective/js/fileupload/resources/js/jquery.fileupload-validate.js
collective/js/fileupload/resources/js/jquery.fileupload.js
collective/js/fileupload/resources/js/jquery.fileupload-image.js
collective/js/fileupload/resources/js/jquery.fileupload-angular.js
collective/js/fileupload/resources/js/jquery.fileupload-audio.js
collective/js/fileupload/resources/js/jquery.fileupload-process.js
collective/js/fileupload/resources/js/main.js
collective/js/fileupload/resources/js/vendor/jquery.ui.widget.js
collective/js/fileupload/resources/js/cors/jquery.xdr-transport.js
collective/js/fileupload/resources/js/cors/jquery.postmessage-transport.js
collective/js/fileupload/resources/css/jquery.fileupload-ui.css
collective/js/fileupload/resources/css/jquery.fileupload.css
collective/js/fileupload/resources/css/demo-ie8.css
collective/js/fileupload/resources/css/jquery.fileupload-ui-noscript.css
collective/js/fileupload/resources/css/jquery.fileupload-noscript.css
collective/js/fileupload/resources/css/style.css
collective/js/fileupload/resources/css/demo.css
collective.js.fileupload-9.12.3.post2.dist-info/top_level.txt
collective.js.fileupload-9.12.3.post2.dist-info/METADATA
collective.js.fileupload-9.12.3.post2.dist-info/DESCRIPTION.rst
collective.js.fileupload-9.12.3.post2.dist-info/entry_points.txt
collective.js.fileupload-9.12.3.post2.dist-info/WHEEL
collective.js.fileupload-9.12.3.post2.dist-info/RECORD
collective.js.fileupload-9.12.3.post2.dist-info/metadata.json
collective.js.fileupload-9.12.3.post2.dist-info/namespace_packages.txt
