Metadata-Version: 2.0
Name: collective.js.fileupload
Version: 9.12.3.post2
Summary: Integration of  jQuery File Upload, an open source File Upload widget with multiple file selection, in Plone.
Home-page: https://github.com/collective/collective.js.fileupload
Author: Rodrigo Ferreira de Souza aka rodfersou
Author-email: rodfersou@gmail.com
License: UNKNOWN
Keywords: plone upload html5
Platform: UNKNOWN
Classifier: Development Status :: 5 - Production/Stable
Classifier: Environment :: Web Environment
Classifier: Framework :: Plone :: 4.0
Classifier: Framework :: Plone :: 4.1
Classifier: Framework :: Plone :: 4.2
Classifier: Framework :: Plone :: 4.3
Classifier: Framework :: Plone
Classifier: Intended Audience :: System Administrators
Classifier: License :: OSI Approved :: GNU General Public License v2 (GPLv2)
Classifier: Operating System :: OS Independent
Classifier: Programming Language :: JavaScript
Classifier: Programming Language :: Python :: 2.6
Classifier: Programming Language :: Python :: 2.7
Classifier: Programming Language :: Python
Classifier: Topic :: Software Development :: Libraries :: Python Modules
Requires-Dist: setuptools
Provides-Extra: test
Requires-Dist: plone.app.testing; extra == 'test'
